<Properties StartupConfiguration="{9F9DA645-8438-4B9D-A89B-1CB03595F208}|Default">
  <MonoDevelop.Ide.ItemProperties.Application.iOS PreferredExecutionTarget="MonoDevelop.IPhone.IPhoneSimulatorTarget.3FF0FA9F-427C-473D-8E05-1C4173EF1A31" />
  <MonoDevelop.Ide.Workbench ActiveDocument="src/iOS/Page/Account/Account.cs">
    <Files>
      <File FileName="src/iOS/Page/Dashboard.cs" Line="9" Column="25" />
      <File FileName="src/iOS/Page/BasePage/BasePageSideMenu.cs" Line="1" Column="1" />
      <File FileName="src/Core/ViewModels/Base/ProjectNavigationBaseViewModel.cs" Line="1" Column="1" />
      <File FileName="src/iOS/Page/Account/Account.cs" Line="24" Column="62" />
      <File FileName="src/Core/ViewModels/Account/AccountViewModel.cs" Line="1" Column="1" />
      <File FileName="src/iOS/Storyboard/Main.storyboard" />
      <File FileName="src/iOS/Page/Librarys/Library.designer.cs" Line="1" Column="1" />
      <File FileName="src/Core/Helpers/PageConstants.cs" Line="21" Column="61" />
      <File FileName="src/Core/Services/MockServices/RealServices/MenuService.cs" Line="31" Column="31" />
      <File FileName="src/iOS/Page/Account/Account.designer.cs" Line="1" Column="1" />
      <File FileName="src/iOS/Page/Account/AccountDescriptions.cs" Line="43" Column="1" />
      <File FileName="src/iOS/Page/Librarys/Library.cs" Line="21" Column="62" />
      <File FileName="src/Core/ViewModels/Library/LibraryViewModel.cs" Line="19" Column="34" />
      <File FileName="src/iOS/CellView/AccountCell.cs" Line="21" Column="1" />
      <File FileName="src/iOS/Views/Cell/Library/CategoryCell.cs" Line="18" Column="1" />
      <File FileName="src/iOS/CellView/AccountCell.designer.cs" Line="1" Column="1" />
      <File FileName="src/iOS/Views/Cell/Account/AccountSaveData.cs" Line="37" Column="16" />
      <File FileName="src/iOS/Views/Cell/Library/CategoryCell.designer.cs" Line="1" Column="1" />
      <File FileName="src/iOS/Page/BasePage/BasePage.cs" Line="45" Column="39" />
      <File FileName="../Core/Int.iOS/Factories/Adapter/ComponentViewSourceFactory.cs" Line="46" Column="46" />
    </Files>
    <Pads>
      <Pad Id="MonoDevelop.Debugger.WatchPad">
        <State />
      </Pad>
    </Pads>
  </MonoDevelop.Ide.Workbench>
  <MonoDevelop.Ide.Workspace ActiveConfiguration="Debug" />
  <MonoDevelop.Ide.ItemProperties.Application.Droid AndroidDesignerPreferredDevice="Nexus 4" PreferredExecutionTarget="Android.4df1efa97c4e5fa7" />
  <MonoDevelop.Ide.DebuggingService.Breakpoints>
    <BreakpointStore>
      <Breakpoint enabled="false" file="/Users/bss/Documents/Projects/Core/Int.Core/Data/Repository/Akavache/RxFeedRepository.cs" line="73" column="23" />
      <Breakpoint enabled="false" file="/Users/bss/Documents/Projects/Thesis/src/Core/Helpers/Manager/LocalBooksManager.cs" relfile="src/Core/Helpers/Manager/LocalBooksManager.cs" line="103" column="1" />
      <Breakpoint enabled="false" file="/Users/bss/Documents/Projects/Thesis/src/iOS/CellView/Product/ProductSource.cs" relfile="src/iOS/CellView/Product/ProductSource.cs" line="78" column="71" />
    </BreakpointStore>
  </MonoDevelop.Ide.DebuggingService.Breakpoints>
  <MonoDevelop.Ide.DebuggingService.PinnedWatches />
  <MultiItemStartupConfigurations />
</Properties>